pyesx/__init__.py
pyesx/analysis.py
pyesx/data.py
pyesx/lib.py
pyesx/path.py
pyesx/plots.py
pyesx/run.py
pyesx/simulation.py
pyesx/utils.py
pyesx/lib/RUN_ex.sh
pyesx-0.1.0.dist-info/METADATA
pyesx-0.1.0.dist-info/RECORD
pyesx-0.1.0.dist-info/WHEEL
pyesx-0.1.0.dist-info/top_level.txt
