Metadata-Version: 2.1
Name: pyesx
Version: 0.1.0
Summary: Python modules associated to the ESX model
Home-page: UNKNOWN
Author: Arthur Enguehard
Author-email: arthur.enguehard@ens.fr
License: GPL license v3
Platform: UNKNOWN
Classifier: Programming Language :: Python :: 3
Classifier: Development Status :: 4 - Beta
Classifier: Framework :: IPython
Classifier: Intended Audience :: Science/Research
Classifier: Natural Language :: English
Classifier: Topic :: Scientific/Engineering :: Atmospheric Science
Requires-Dist: numpy
Requires-Dist: pandas
Requires-Dist: jdcal
Requires-Dist: datetime
Requires-Dist: matplotlib
